taskel/__init__.py
taskel-0.0.3.dist-info/METADATA
taskel-0.0.3.dist-info/WHEEL
taskel-0.0.3.dist-info/top_level.txt
taskel-0.0.3.dist-info/RECORD
