Metadata-Version: 2.1
Name: taskel
Version: 0.0.3
Summary: The python library for all types of tasks
Home-page: http://github.com/Ehnryu/taskel
Author: Ehnryu/Sakurai07
Author-email: blzzardst0rm@gmail.com
License: MIT
Keywords: taskel,tasks,threading
Platform: UNKNOWN
